{
  "mypage": {
    "id": 0,
    "nickname": "홍길동",
    "email": "terxt132@naver.com",
    "introduce": "255자로 제한하기로 했어요  255자로 제한하기로 했어요  255자로 제한하기로 했어요  255자로 제한하기로 했어요  255자로 제한하기로 했어요  255자로 제한하기로 했어요  255자로 제한하기로 했어요  255자로 제한하기로 했어요  255자로 제한하기로 했어요  255자로 제한",
    "phoneNum": "010-5555-5555",
    "dogList": [
      {
        "id": 0,
        "name": "노을",
        "gender": "여",
        "size": "소형",
        "dogImageFiles": [
          {
            "id": 0,
            "imageUrl": "https://ifh.cc/g/zBph8p.jpg"
          }
        ],
        "isRepresentative": false
      },
      {
        "id": 1,
        "name": "구름",
        "gender": "여",
        "size": "소형",
        "dogImageFiles": [
          {
            "id": 0,
            "imageUrl": "https://ifh.cc/g/dBbqYO.jpg"
          }
        ],
        "isRepresentative": true
      }
    ],
    "myPostList": [
      {
        "id": 0,
        "title": "강아지 산책시켜 주세요",
        "modifiedAt": "게시글 수정일자",
        "isComplete": true
      },
      {
        "id": 1,
        "title": "우리 노을이 산책 맡아주실분",
        "modifiedAt": "게시글 수정일자",
        "isComplete": false
      }
    ],
    "reviewList": [
      {
        "id": 0,
        "writer": "행배",
        "comment": "재밌는 산책이였어요!",
        "imagePath": "https://ifh.cc/g/gKSg6l.jpg"
      },
      {
        "id": 1,
        "writer": "민식이",
        "comment": "똥을 주워먹더군요...ㅠㅠ",
        "imagePath": "https://ifh.cc/g/6zoHz0.jpg"
      }
    ]
  },
  "user": [
    {
      "id": 1,
      "username": "userid",
      "password": "pw12345",
      "nickname": "닉네임",
      "email": "test@test.com",
      "address": "서울시 멍친구",
      "latitude": "위도",
      "longitude": "경도",
      "isAgree": true
    },
    {
      "username": "test1",
      "password": "test1234",
      "nickname": "nickname1",
      "email": "test@tes.com",
      "address": "강원 원주시 라옹정길 1",
      "isAgree": true,
      "latitude": "37.3186533214793",
      "longitude": "127.964873643679",
      "id": 2
    },
    {
      "username": "asdf",
      "password": "asdf1111",
      "nickname": "asdfasdf",
      "email": "asdfs@an.co",
      "address": "부산 해운대구 APEC로 17",
      "isAgree": true,
      "latitude": "35.1659324519479",
      "longitude": "129.132411521392",
      "id": 3
    }
  ],
  "mung": [
    {
      "id": 0,
      "name": "노을",
      "gender": "여",
      "age": 1,
      "size": "소형",
      "dogImageFiles": [
        {
          "id": 0,
          "imageUrl": "https://ifh.cc/g/zBph8p.jpg"
        }
      ],
      "isRepresentative": false
    },
    {
      "id": 1,
      "name": "구름",
      "gender": "여",
      "age": 13,
      "size": "소형",
      "dogImageFiles": [
        {
          "id": 0,
          "imageUrl": "https://ifh.cc/g/dBbqYO.jpg"
        }
      ],
      "isRepresentative": true
    }
  ],
  "dogList": [
          {
        "id": 0,
        "name": "노을",
        "gender": "여",
        "size": "소형",
        "dogImageFiles": [
          {
            "id": 0,
            "imageUrl": "https://ifh.cc/g/zBph8p.jpg"
          }
        ],
        "isRepresentative": false
      },
    {
      "id": 1,
      "name": "구름",
      "gender": "여",
      "size": "소형",
      "dogImageFiles": [
        {
          "id": 0,
          "imageUrl": "https://ifh.cc/g/dBbqYO.jpg"
        }
      ],
      "isRepresentative": true
    }
  ],
  "post": [
    {
      "nickname": "서동현",
      "title": "헤드라인은 두번째 줄까지 노출됩니다.",
      "requestStartDate": "2022.02.04T12:44",
      "requestEndDate": "2022.02.04T13:44",
      "applyCount": 22,
      "applyByMe": true,
      "isComplete": true,
      "content": "상세내용이에요",
      "imagePath": [
        "https://ifh.cc/g/GFpGa0.png",
        "https://ifh.cc/g/j6Cb8M.jpg"
      ],
      "id": 1
    },
    {
      "nickname": "김형준",
      "title": "산책메이트 구해요",
      "requestStartDate": "2022.02.06T12:44",
      "requestEndDate": "2022.02.06T13:44",
      "applyCount": 2,
      "applyByMe": true,
      "isComplete": true,
      "content": "상세내용이에요2222",
      "imagePath": [
        "https://ifh.cc/g/fcv8X4.jpg"
      ],
      "id": 2
    },
    {
      "nickname": "인기천",
      "title": "산책산책산책산책",
      "requestStartDate": "2022.02.06T12:44",
      "requestEndDate": "2022.02.06T13:44",
      "applyCount": 2,
      "applyByMe": true,
      "isComplete": false,
      "content": "상세내용입니다",
      "imagePath": [
        "https://ifh.cc/g/ttcwoL.png"
      ],
      "id": 3
    },
    {
      "nickname": "용희님 성을 까먹었다",
      "title": "떡실신 몽뭉이",
      "requestStartDate": "2022.02.06T12:44",
      "requestEndDate": "2022.02.06T13:44",
      "applyCount": 2,
      "applyByMe": true,
      "isComplete": true,
      "content": "상세내용이에요33333",
      "imagePath": [
        "https://ifh.cc/g/tBcpcD.jpg",
        "https://ifh.cc/g/B21g89.jpg"
      ],
      "id": 3
    }
  ]
}